sentor/__init__.py
sentor/client.py
sentor/exceptions.py
tests/__init__.py
tests/test_client.py
sentor-0.1.0.dist-info/METADATA
sentor-0.1.0.dist-info/WHEEL
sentor-0.1.0.dist-info/entry_points.txt
sentor-0.1.0.dist-info/top_level.txt
sentor-0.1.0.dist-info/RECORD
