Metadata-Version: 2.4
Name: sentor
Version: 0.1.0
Requires-Dist: requests>=2.28.0
Dynamic: requires-dist
